{"query":{"categorymembers":[{"pageid":2151,"ns":0,"title":"100 doors"},{"pageid":4938,"ns":0,"title":"24 game"},{"pageid":2663,"ns":0,"title":"99 Bottles of Beer"},{"pageid":6812,"ns":0,"title":"A+B"},{"pageid":3131,"ns":0,"title":"Abstract type"},{"pageid":5255,"ns":0,"title":"Accumulator factory"},{"pageid":3050,"ns":0,"title":"Ackermann function"},{"pageid":3099,"ns":0,"title":"Active object"},{"pageid":2135,"ns":0,"title":"Add a variable to a class instance at runtime"},{"pageid":1985,"ns":0,"title":"Address of a variable"},{"pageid":3114,"ns":0,"title":"Align columns"},{"pageid":2774,"ns":0,"title":"Amb"},{"pageid":3052,"ns":0,"title":"Anagrams"},{"pageid":9632,"ns":0,"title":"Anagrams\/Deranged anagrams"},{"pageid":4669,"ns":0,"title":"Animate a pendulum"},{"pageid":4381,"ns":0,"title":"Animation"},{"pageid":8846,"ns":0,"title":"Anonymous recursion"},{"pageid":1639,"ns":0,"title":"Apply a callback to an array"},{"pageid":6036,"ns":0,"title":"Arbitrary-precision integers (included)"},{"pageid":4028,"ns":0,"title":"Arena storage pool"},{"pageid":2414,"ns":0,"title":"Arithmetic evaluation"},{"pageid":11377,"ns":0,"title":"Arithmetic-geometric mean"},{"pageid":2688,"ns":0,"title":"Arithmetic\/Complex"},{"pageid":2069,"ns":0,"title":"Arithmetic\/Integer"},{"pageid":3370,"ns":0,"title":"Arithmetic\/Rational"},{"pageid":4833,"ns":0,"title":"Array concatenation"},{"pageid":4613,"ns":0,"title":"Arrays"},{"pageid":3353,"ns":0,"title":"Assertions"},{"pageid":1642,"ns":0,"title":"Associative arrays\/Creation"},{"pageid":4633,"ns":0,"title":"Associative arrays\/Iteration"},{"pageid":4178,"ns":0,"title":"Atomic updates"},{"pageid":2412,"ns":0,"title":"Averages\/Arithmetic mean"},{"pageid":4376,"ns":0,"title":"Averages\/Median"},{"pageid":4377,"ns":0,"title":"Averages\/Mode"},{"pageid":6095,"ns":0,"title":"Averages\/Pythagorean means"},{"pageid":6099,"ns":0,"title":"Averages\/Root mean square"},{"pageid":4400,"ns":0,"title":"Averages\/Simple moving average"},{"pageid":9279,"ns":0,"title":"Balanced brackets"},{"pageid":8971,"ns":0,"title":"Best shuffle"},{"pageid":10041,"ns":0,"title":"Binary digits"},{"pageid":2206,"ns":0,"title":"Binary search"},{"pageid":4071,"ns":0,"title":"Binary strings"},{"pageid":3212,"ns":0,"title":"Bitmap"},{"pageid":3214,"ns":0,"title":"Bitmap\/Bresenham's line algorithm"},{"pageid":3219,"ns":0,"title":"Bitmap\/B\u00e9zier curves\/Cubic"},{"pageid":3213,"ns":0,"title":"Bitmap\/B\u00e9zier curves\/Quadratic"},{"pageid":3562,"ns":0,"title":"Bitmap\/Flood fill"},{"pageid":3226,"ns":0,"title":"Bitmap\/Histogram"},{"pageid":3218,"ns":0,"title":"Bitmap\/Midpoint circle algorithm"},{"pageid":3225,"ns":0,"title":"Bitmap\/Read a PPM file"},{"pageid":3216,"ns":0,"title":"Bitmap\/Write a PPM file"},{"pageid":3266,"ns":0,"title":"Bitwise IO"},{"pageid":2251,"ns":0,"title":"Bitwise operations"},{"pageid":4490,"ns":0,"title":"Boolean values"},{"pageid":9399,"ns":0,"title":"Box the compass"},{"pageid":10244,"ns":0,"title":"Break OO privacy"},{"pageid":4126,"ns":0,"title":"Bulls and cows"},{"pageid":7508,"ns":0,"title":"Bulls and cows\/Player"},{"pageid":9913,"ns":0,"title":"Caesar cipher"},{"pageid":9818,"ns":0,"title":"Calendar"},{"pageid":9832,"ns":0,"title":"Calendar - for \"real\" programmers"},{"pageid":4711,"ns":0,"title":"Call a foreign-language function"},{"pageid":10098,"ns":0,"title":"Call a function"},{"pageid":3999,"ns":0,"title":"Call a function in a shared library"},{"pageid":9220,"ns":0,"title":"Case-sensitivity of identifiers"},{"pageid":9246,"ns":0,"title":"Catalan numbers"},{"pageid":3118,"ns":0,"title":"Character codes"},{"pageid":8493,"ns":0,"title":"Character matching"},{"pageid":8970,"ns":0,"title":"Chat server"},{"pageid":7914,"ns":0,"title":"Checkpoint synchronization"},{"pageid":9335,"ns":0,"title":"Cholesky decomposition"},{"pageid":1844,"ns":0,"title":"Classes"},{"pageid":4142,"ns":0,"title":"Closest-pair problem"},{"pageid":1635,"ns":0,"title":"Collections"},{"pageid":2405,"ns":0,"title":"Combinations"},{"pageid":8749,"ns":0,"title":"Combinations with repetitions"},{"pageid":1937,"ns":0,"title":"Command-line arguments"},{"pageid":1996,"ns":0,"title":"Comments"},{"pageid":5380,"ns":0,"title":"Compile-time calculation"},{"pageid":1969,"ns":0,"title":"Compound data type"},{"pageid":1915,"ns":0,"title":"Concurrent computing"},{"pageid":1787,"ns":0,"title":"Conditional structures"},{"pageid":11330,"ns":0,"title":"Conjugate transpose"},{"pageid":3211,"ns":0,"title":"Constrained genericity"},{"pageid":8230,"ns":0,"title":"Constrained random points on a circle"},{"pageid":11445,"ns":0,"title":"Continued fraction"},{"pageid":9912,"ns":0,"title":"Convert decimal number to rational"},{"pageid":3076,"ns":0,"title":"Conway's Game of Life"},{"pageid":1965,"ns":0,"title":"Copy a string"},{"pageid":9012,"ns":0,"title":"Count in factors"},{"pageid":9879,"ns":0,"title":"Count in octal"},{"pageid":9932,"ns":0,"title":"Count occurrences of a substring"},{"pageid":10731,"ns":0,"title":"Count the coins"},{"pageid":10966,"ns":0,"title":"CRC-32"},{"pageid":2027,"ns":0,"title":"Create a file"},{"pageid":1982,"ns":0,"title":"Create a two-dimensional array at runtime"},{"pageid":9338,"ns":0,"title":"Create an HTML table"},{"pageid":4347,"ns":0,"title":"Create an object at a given address"},{"pageid":8707,"ns":0,"title":"CSV to HTML translation"},{"pageid":2098,"ns":0,"title":"Date format"}]},"query-continue":{"categorymembers":{"cmcontinue":"page|44415445204d414e4950554c4154494f4e|4157"}}}